nobbofin_tools/importers/__init__.py
nobbofin_tools/importers/dkbvisa.py
nobbofin_tools/importers/fints.py
nobbofin_tools-0.1.1.dist-info/WHEEL
nobbofin_tools-0.1.1.dist-info/METADATA
nobbofin_tools-0.1.1.dist-info/RECORD
