Metadata-Version: 2.1
Name: nobbofin-tools
Version: 0.1.1
Summary: 
Home-page: UNKNOWN
License: UNKNOWN
Author: Enno Lohmeier
Author-email: enno@nerdworks.de
Requires-Python: >=3.7,<4.0
Classifier: Programming Language :: Python :: 3
Classifier: Programming Language :: Python :: 3.7
Requires-Dist: beancount (>=2.1,<3.0)
Requires-Dist: simplejson (>=3.16,<4.0)
